<?xml version="1.0" encoding="utf-8" ?>
<dwsync>
<file name="Oct-2021.tar.gz" server="control.asu.edu" local="132775459200000000" remote="132834334800000000" Dst="0" />
<file name="Sep-2021.tar.gz" server="control.asu.edu" local="132774595800000000" remote="132834334800000000" Dst="0" />
<file name="Sep-2021.tar.gz.1" server="control.asu.edu" local="132773732400000000" remote="132834334800000000" Dst="0" />
<file name="Sep-2021.tar.gz.2" server="control.asu.edu" local="132772867200000000" remote="132834334800000000" Dst="0" />
<file name="Sep-2021.tar.gz.3" server="control.asu.edu" local="132772003800000000" remote="132834334800000000" Dst="0" />
<file name="Oct-2021.tar.gz" server="10.120.70.135" local="132775459200000000" remote="133134960130000000" Dst="0" />
<file name="Sep-2021.tar.gz" server="10.120.70.135" local="132774595800000000" remote="133134960140000000" Dst="0" />
<file name="Sep-2021.tar.gz.1" server="10.120.70.135" local="132773732400000000" remote="133134960140000000" Dst="0" />
<file name="Sep-2021.tar.gz.2" server="10.120.70.135" local="132772867200000000" remote="133134960140000000" Dst="0" />
<file name="Sep-2021.tar.gz.3" server="10.120.70.135" local="132772003800000000" remote="133295708450000000" Dst="0" />
</dwsync>